chatwoot_client/__init__.py
chatwoot_client/api_client.py
chatwoot_client/configuration.py
chatwoot_client/rest.py
chatwoot_client/apis/__init__.py
chatwoot_client/apis/account_agent_bots_api.py
chatwoot_client/apis/account_users_api.py
chatwoot_client/apis/accounts_api.py
chatwoot_client/apis/agent_bots_api.py
chatwoot_client/apis/agents_api.py
chatwoot_client/apis/automation_rule_api.py
chatwoot_client/apis/canned_response_api.py
chatwoot_client/apis/canned_responses_api.py
chatwoot_client/apis/contact_api.py
chatwoot_client/apis/contacts_api.py
chatwoot_client/apis/contacts_api_api.py
chatwoot_client/apis/conversation_assignment_api.py
chatwoot_client/apis/conversation_labels_api.py
chatwoot_client/apis/conversations_api.py
chatwoot_client/apis/conversations_api_api.py
chatwoot_client/apis/csat_survey_page_api.py
chatwoot_client/apis/custom_attributes_api.py
chatwoot_client/apis/custom_filters_api.py
chatwoot_client/apis/help_center_api.py
chatwoot_client/apis/inbox_api_api.py
chatwoot_client/apis/inboxes_api.py
chatwoot_client/apis/integrations_api.py
chatwoot_client/apis/messages_api.py
chatwoot_client/apis/messages_api_api.py
chatwoot_client/apis/profile_api.py
chatwoot_client/apis/reports_api.py
chatwoot_client/apis/teams_api.py
chatwoot_client/apis/users_api.py
chatwoot_client/apis/webhooks_api.py
chatwoot_client/models/__init__.py
chatwoot_client/models/account.py
chatwoot_client/models/account_create_update_payload.py
chatwoot_client/models/account_id_account_users_body.py
chatwoot_client/models/account_id_account_users_body1.py
chatwoot_client/models/account_id_agents_body.py
chatwoot_client/models/account_id_conversations_body.py
chatwoot_client/models/account_id_inbox_members_body.py
chatwoot_client/models/account_id_inbox_members_body1.py
chatwoot_client/models/account_id_inbox_members_body2.py
chatwoot_client/models/account_id_inboxes_body.py
chatwoot_client/models/account_summary.py
chatwoot_client/models/account_summary_previous.py
chatwoot_python_client-1.0.0.16.dist-info/licenses/LICENSE
chatwoot_python_client-1.0.0.16.dist-info/METADATA
chatwoot_python_client-1.0.0.16.dist-info/WHEEL
chatwoot_python_client-1.0.0.16.dist-info/top_level.txt
chatwoot_python_client-1.0.0.16.dist-info/RECORD
