Metadata-Version: 2.4
Name: chatwoot-python-client
Version: 1.0.0.16
Summary: Chatwoot
Home-page: 
Author-email: hello@chatwoot.com
Keywords: Swagger,Chatwoot
License-File: LICENSE
Requires-Dist: urllib3>=1.15
Requires-Dist: six>=1.10
Requires-Dist: certifi
Requires-Dist: python-dateutil
Dynamic: author-email
Dynamic: description
Dynamic: keywords
Dynamic: license-file
Dynamic: requires-dist
Dynamic: summary
